{"stat.walkOneCm":41940,"achievement.openInventory":8,"stat.pickup.minecraft.repeater":4,"stat.mineBlock.minecraft.stone_button":1,"stat.useItem.minecraft.stone":1,"stat.useItem.minecraft.repeater":4,"stat.leaveGame":1,"stat.mineBlock.minecraft.cobblestone":17,"stat.useItem.minecraft.lava_bucket":1,"stat.pickup.minecraft.cobblestone":18,"stat.useItem.minecraft.bucket":1,"stat.jump":60,"stat.playOneMinute":11262,"stat.pickup.minecraft.stone_button":1,"stat.fallOneCm":209,"stat.craftItem.minecraft.stone_button":1,"stat.useItem.minecraft.redstone":2,"stat.pickup.minecraft.redstone":1,"stat.timeSinceDeath":11262,"stat.breakItem.minecraft.iron_pickaxe":1,"stat.pickup.minecraft.dirt":32,"stat.useItem.minecraft.dirt":43,"stat.useItem.minecraft.stone_button":2,"stat.useItem.minecraft.iron_pickaxe":19,"stat.mineBlock.minecraft.dirt":34,"stat.mineBlock.minecraft.stone":1,"achievement.exploreAllBiomes":{"value":0,"progress":["Plains"]},"stat.useItem.minecraft.iron_shovel":9}